tavern/__init__.py
tavern/core.py
tavern/entry.py
tavern/helpers.py
tavern/request.py
tavern/response.py
tavern/_core/__init__.py
tavern/_core/dict_util.py
tavern/_core/exceptions.py
tavern/_core/extfunctions.py
tavern/_core/formatted_str.py
tavern/_core/general.py
tavern/_core/jmesutils.py
tavern/_core/loader.py
tavern/_core/plugins.py
tavern/_core/report.py
tavern/_core/run.py
tavern/_core/skip.py
tavern/_core/stage_lines.py
tavern/_core/strict_util.py
tavern/_core/strtobool.py
tavern/_core/testhelpers.py
tavern/_core/tincture.py
tavern/_core/pytest/__init__.py
tavern/_core/pytest/config.py
tavern/_core/pytest/error.py
tavern/_core/pytest/file.py
tavern/_core/pytest/hooks.py
tavern/_core/pytest/item.py
tavern/_core/pytest/newhooks.py
tavern/_core/pytest/util.py
tavern/_core/schema/__init__.py
tavern/_core/schema/extensions.py
tavern/_core/schema/files.py
tavern/_core/schema/jsonschema.py
tavern/_core/schema/tests.jsonschema.yaml
tavern/_core/schema/tests.schema.yaml
tavern/_plugins/__init__.py
tavern/_plugins/grpc/__init__.py
tavern/_plugins/grpc/client.py
tavern/_plugins/grpc/jsonschema.yaml
tavern/_plugins/grpc/protos.py
tavern/_plugins/grpc/request.py
tavern/_plugins/grpc/response.py
tavern/_plugins/grpc/schema.yaml
tavern/_plugins/grpc/tavernhook.py
tavern/_plugins/mqtt/__init__.py
tavern/_plugins/mqtt/client.py
tavern/_plugins/mqtt/jsonschema.yaml
tavern/_plugins/mqtt/request.py
tavern/_plugins/mqtt/response.py
tavern/_plugins/mqtt/schema.yaml
tavern/_plugins/mqtt/tavernhook.py
tavern/_plugins/rest/__init__.py
tavern/_plugins/rest/files.py
tavern/_plugins/rest/request.py
tavern/_plugins/rest/response.py
tavern/_plugins/rest/tavernhook.py
tavern-3.0.1.dist-info/entry_points.txt
tavern-3.0.1.dist-info/licenses/LICENSE
tavern-3.0.1.dist-info/WHEEL
tavern-3.0.1.dist-info/METADATA
tavern-3.0.1.dist-info/RECORD
