Metadata-Version: 2.4
Name: tavern
Version: 3.0.1
Summary: Simple testing of RESTful APIs
Keywords: testing,pytest
Author: Michael Boulton
Requires-Python: >=3.11
Classifier: Development Status :: 5 - Production/Stable
Classifier: Intended Audience :: Developers
Classifier: Framework :: Pytest
Classifier: Programming Language :: Python :: 3
Classifier: Programming Language :: Python :: 3.11
Classifier: Programming Language :: Python :: 3.12
Classifier: Programming Language :: Python :: 3.13
Classifier: Topic :: Utilities
Classifier: Topic :: Software Development :: Testing
Classifier: License :: OSI Approved :: MIT License
License-File: LICENSE
Requires-Dist: PyYAML>=6.0.1,<7
Requires-Dist: jmespath>=1,<2
Requires-Dist: jsonschema>=4,<5
Requires-Dist: pyjwt>=2.5.0,<3
Requires-Dist: pykwalify>=1.8.0,<2
Requires-Dist: pytest>=8,<10
Requires-Dist: python-box>=6,<7
Requires-Dist: requests>=2.22.0,<3
Requires-Dist: simpleeval>=1.0.3
Requires-Dist: stevedore>=4,<5
Requires-Dist: Faker ; extra == "dev"
Requires-Dist: allure-pytest ; extra == "dev"
Requires-Dist: colorlog ; extra == "dev"
Requires-Dist: flask>=3,<4 ; extra == "dev"
Requires-Dist: fluent-logger ; extra == "dev"
Requires-Dist: itsdangerous ; extra == "dev"
Requires-Dist: coverage[toml] ; extra == "dev"
Requires-Dist: flit >=3.2,<4 ; extra == "dev"
Requires-Dist: wheel ; extra == "dev"
Requires-Dist: pre-commit ; extra == "dev"
Requires-Dist: pytest-cov ; extra == "dev"
Requires-Dist: pytest-xdist ; extra == "dev"
Requires-Dist: py ; extra == "dev"
Requires-Dist: tox>=4,<5 ; extra == "dev"
Requires-Dist: ruff~=0.9.10 ; extra == "dev"
Requires-Dist: uv>=0.9.2 ; extra == "dev"
Requires-Dist: types-PyYAML ; extra == "dev"
Requires-Dist: types-protobuf>=5,<6 ; extra == "dev"
Requires-Dist: protobuf-protoc-bin==29.5 ; extra == "dev"
Requires-Dist: grpcio-tools ; extra == "dev"
Requires-Dist: types-requests ; extra == "dev"
Requires-Dist: types-jsonschema ; extra == "dev"
Requires-Dist: types-paho-mqtt ; extra == "dev"
Requires-Dist: types-jmespath ; extra == "dev"
Requires-Dist: grpc-interceptor ; extra == "dev"
Requires-Dist: exceptiongroup ; extra == "dev"
Requires-Dist: tomli ; extra == "dev"
Requires-Dist: tbump>=6.10.0 ; extra == "dev"
Requires-Dist: tox>4.20,<5 ; extra == "dev"
Requires-Dist: sphinx>=7,<8 ; extra == "docs"
Requires-Dist: sphinx_rtd_theme ; extra == "docs"
Requires-Dist: recommonmark ; extra == "docs"
Requires-Dist: commonmark ; extra == "docs"
Requires-Dist: docutils ; extra == "docs"
Requires-Dist: pygments ; extra == "docs"
Requires-Dist: sphinx-markdown-tables ; extra == "docs"
Requires-Dist: grpcio ; extra == "grpc"
Requires-Dist: grpcio-reflection ; extra == "grpc"
Requires-Dist: grpcio-status ; extra == "grpc"
Requires-Dist: google-api-python-client ; extra == "grpc"
Requires-Dist: protobuf>=5,<6 ; extra == "grpc"
Requires-Dist: proto-plus ; extra == "grpc"
Requires-Dist: paho-mqtt>=1.3.1,<=1.6.1 ; extra == "mqtt"
Project-URL: Documentation, https://tavern.readthedocs.io/en/latest/
Project-URL: Home, https://taverntesting.github.io/
Project-URL: Source, https://github.com/taverntesting/tavern
Provides-Extra: dev
Provides-Extra: docs
Provides-Extra: grpc
Provides-Extra: mqtt
